LICENSE
README.md
setup.cfg
setup.py
/rds/project/rds-5mCMIDBOkPU/ma595/detectree2/builds/pb1-detectron2/detectron2/layers/csrc/vision.cpp
/rds/project/rds-5mCMIDBOkPU/ma595/detectree2/builds/pb1-detectron2/detectron2/layers/csrc/ROIAlignRotated/ROIAlignRotated_cpu.cpp
/rds/project/rds-5mCMIDBOkPU/ma595/detectree2/builds/pb1-detectron2/detectron2/layers/csrc/box_iou_rotated/box_iou_rotated_cpu.cpp
/rds/project/rds-5mCMIDBOkPU/ma595/detectree2/builds/pb1-detectron2/detectron2/layers/csrc/cocoeval/cocoeval.cpp
/rds/project/rds-5mCMIDBOkPU/ma595/detectree2/builds/pb1-detectron2/detectron2/layers/csrc/nms_rotated/nms_rotated_cpu.cpp
detectron2/__init__.py
detectron2/checkpoint/__init__.py
detectron2/checkpoint/c2_model_loading.py
detectron2/checkpoint/catalog.py
detectron2/checkpoint/detection_checkpoint.py
detectron2/config/__init__.py
detectron2/config/compat.py
detectron2/config/config.py
detectron2/config/defaults.py
detectron2/config/instantiate.py
detectron2/config/lazy.py
detectron2/data/__init__.py
detectron2/data/benchmark.py
detectron2/data/build.py
detectron2/data/catalog.py
detectron2/data/common.py
detectron2/data/dataset_mapper.py
detectron2/data/detection_utils.py
detectron2/data/datasets/__init__.py
detectron2/data/datasets/builtin.py
detectron2/data/datasets/builtin_meta.py
detectron2/data/datasets/cityscapes.py
detectron2/data/datasets/cityscapes_panoptic.py
detectron2/data/datasets/coco.py
detectron2/data/datasets/coco_panoptic.py
detectron2/data/datasets/lvis.py
detectron2/data/datasets/lvis_v0_5_categories.py
detectron2/data/datasets/lvis_v1_categories.py
detectron2/data/datasets/pascal_voc.py
detectron2/data/datasets/register_coco.py
detectron2/data/samplers/__init__.py
detectron2/data/samplers/distributed_sampler.py
detectron2/data/samplers/grouped_batch_sampler.py
detectron2/data/transforms/__init__.py
detectron2/data/transforms/augmentation.py
detectron2/data/transforms/augmentation_impl.py
detectron2/data/transforms/transform.py
pb1_detectron2.egg-info/PKG-INFO
pb1_detectron2.egg-info/SOURCES.txt
pb1_detectron2.egg-info/dependency_links.txt
pb1_detectron2.egg-info/requires.txt
pb1_detectron2.egg-info/top_level.txt
